KratosMultiphysics/DamApplication/__init__.py
KratosMultiphysics/DamApplication/apply_constraint_vector_dam_table_process.py
KratosMultiphysics/DamApplication/apply_load_vector_dam_process.py
KratosMultiphysics/DamApplication/apply_load_vector_dam_table_process.py
KratosMultiphysics/DamApplication/check_and_prepare_model_process_dam_mechanical.py
KratosMultiphysics/DamApplication/check_and_prepare_model_process_dam_thermal.py
KratosMultiphysics/DamApplication/check_and_prepare_selfweight_model_process_dam.py
KratosMultiphysics/DamApplication/dam_P_solver.py
KratosMultiphysics/DamApplication/dam_UP_mechanical_solver.py
KratosMultiphysics/DamApplication/dam_UP_thermo_mechanic_solver.py
KratosMultiphysics/DamApplication/dam_analysis.py
KratosMultiphysics/DamApplication/dam_cleaning_utility.py
KratosMultiphysics/DamApplication/dam_constitutive_law_utility.py
KratosMultiphysics/DamApplication/dam_construction_utility.py
KratosMultiphysics/DamApplication/dam_eigen_solver.py
KratosMultiphysics/DamApplication/dam_mapping_variables_utility.py
KratosMultiphysics/DamApplication/dam_mechanical_solver.py
KratosMultiphysics/DamApplication/dam_selfweight_solver.py
KratosMultiphysics/DamApplication/dam_thermo_mechanic_solver.py
KratosMultiphysics/DamApplication/gid_dam_output_process.py
KratosMultiphysics/DamApplication/global_joint_stress_utility.py
KratosMultiphysics/DamApplication/impose_2d_random_fields_variable_process.py
KratosMultiphysics/DamApplication/impose_3d_random_fields_variable_process.py
KratosMultiphysics/DamApplication/impose_chemo_mechanical_aging_process.py
KratosMultiphysics/DamApplication/impose_face_heat_flux_process.py
KratosMultiphysics/DamApplication/impose_grouting_reference_temperature_process.py
KratosMultiphysics/DamApplication/impose_heat_source_process.py
KratosMultiphysics/DamApplication/impose_input_table_nodal_young_modulus_process.py
KratosMultiphysics/DamApplication/impose_nodal_reference_temperature_process.py
kratosdamapplication-10.4.0.dist-info/METADATA
kratosdamapplication-10.4.0.dist-info/WHEEL
kratosdamapplication-10.4.0.dist-info/RECORD
